[
  {
    "match_ref": "R1M3",
    "match_id": "R1M3_Furia_vs_Team Heretics_",
    "tournament": "Six Invitational/2026",
    "stage": "Unknown",
    "date": "",
    "map": "Clubhouse",
    "map_raw": "Clubhouse",
    "finished": "true",
    "atk_team": "Furia",
    "def_team": "Team Heretics",
    "atk_score": 4,
    "def_score": 2,
    "atk_deaths": 6,
    "def_deaths": 3,
    "total_deaths": 9,
    "atk_bans": [
      "Bandit",
      "Kaid",
      "Azami",
      "Thermite",
      "Capitao"
    ],
    "def_bans": [
      "Thermite",
      "Capitao",
      "Ace",
      "Bandit",
      "Kaid"
    ],
    "atk_operators": [],
    "def_operators": [],
    "first_attack": "atk",
    "pick": "",
    "is_flawless": false,
    "raw_map_block": "\n        |bantype=siegeX\n        |t1ban1=Bandit|t1ban2=Kaid|t1ban3=Azami|t1ban4=Thermite|t1ban5=Capitao|t1ban6=\n        |t2ban1=Thermite|t2ban2=Capitao|t2ban3=Ace|t2ban4=Bandit|t2ban5=Kaid|t2ban6=\n        |t1firstside=atk|t1firstsideot=\n        |t1atk=4|t1def=3|t1otatk=|t1otdef=\n        |t2atk=0|t2def=2|t2otatk=|t2otdef="
  },
  {
    "match_ref": "R2M1",
    "match_id": "R2M1_Wildcard_vs_Spacestation Gaming_",
    "tournament": "Six Invitational/2026",
    "stage": "Unknown",
    "date": "",
    "map": "Clubhouse",
    "map_raw": "Clubhouse",
    "finished": "skip",
    "atk_team": "Wildcard",
    "def_team": "Spacestation Gaming",
    "atk_score": 0,
    "def_score": 0,
    "atk_deaths": 0,
    "def_deaths": 0,
    "total_deaths": 0,
    "atk_bans": [],
    "def_bans": [],
    "atk_operators": [],
    "def_operators": [],
    "first_attack": "atk",
    "pick": "",
    "is_flawless": false,
    "raw_map_block": "\n        |bantype=siegeX\n        |t1ban1=|t1ban2=|t1ban3=|t1ban4=|t1ban5=|t1ban6=\n        |t2ban1=|t2ban2=|t2ban3=|t2ban4=|t2ban5=|t2ban6=\n        |t1firstside=|t1firstsideot=\n        |t1atk=|t1def=|t1otatk=|t1otdef=\n        |t2atk=|t2def=|t2otatk=|t2otdef="
  },
  {
    "match_ref": "R2M3",
    "match_id": "R2M3_Weibo Gaming_vs_Furia_",
    "tournament": "Six Invitational/2026",
    "stage": "Unknown",
    "date": "",
    "map": "Clubhouse",
    "map_raw": "Clubhouse",
    "finished": "true",
    "atk_team": "Furia",
    "def_team": "Weibo Gaming",
    "atk_score": 4,
    "def_score": 2,
    "atk_deaths": 6,
    "def_deaths": 6,
    "total_deaths": 12,
    "atk_bans": [
      "Ace",
      "Hibana",
      "Grim",
      "Kaid",
      "Azami",
      "Clash"
    ],
    "def_bans": [
      "Bandit",
      "Kaid",
      "Mira",
      "Ace",
      "Thermite",
      "Capitao"
    ],
    "atk_operators": [],
    "def_operators": [],
    "first_attack": "def",
    "pick": "",
    "is_flawless": false,
    "raw_map_block": "\n        |bantype=siegeX\n        |t1ban1=Ace|t1ban2=Hibana|t1ban3=Grim|t1ban4=Kaid|t1ban5=Azami|t1ban6=Clash\n        |t2ban1=Bandit|t2ban2=Kaid|t2ban3=Mira|t2ban4=Ace|t2ban5=Thermite|t2ban6=Capitao\n        |t1firstside=def|t1firstsideot=\n        |t1atk=3|t1def=2|t1otatk=|t1otdef=\n        |t2atk=4|t2def=3|t2otatk=|t2otdef="
  },
  {
    "match_ref": "R4M1",
    "match_id": "R4M1_Wildcard_vs_FaZe Clan_",
    "tournament": "Six Invitational/2026",
    "stage": "Unknown",
    "date": "",
    "map": "Clubhouse",
    "map_raw": "Clubhouse",
    "finished": "true",
    "atk_team": "FaZe Clan",
    "def_team": "Wildcard",
    "atk_score": 3,
    "def_score": 3,
    "atk_deaths": 6,
    "def_deaths": 6,
    "total_deaths": 12,
    "atk_bans": [
      "Thermite",
      "Grim",
      "Blackbeard",
      "Kaid",
      "Bandit",
      "Azami"
    ],
    "def_bans": [
      "Kaid",
      "Bandit",
      "Mira",
      "Thermite",
      "Maverick",
      "Ace"
    ],
    "atk_operators": [],
    "def_operators": [],
    "first_attack": "def",
    "pick": "",
    "is_flawless": false,
    "raw_map_block": "\n        |bantype=siegeX\n        |t1ban1=Thermite|t1ban2=Grim|t1ban3=Blackbeard|t1ban4=Kaid|t1ban5=Bandit|t1ban6=Azami\n        |t2ban1=Kaid|t2ban2=Bandit|t2ban3=Mira|t2ban4=Thermite|t2ban5=Maverick|t2ban6=Ace\n        |t1firstside=def|t1firstsideot=atk\n        |t1atk=3|t1def=3|t1otatk=0|t1otdef=0\n        |t2atk=3|t2def=3|t2otatk=1|t2otdef=1"
  },
  {
    "match_ref": "R4M2",
    "match_id": "R4M2_Furia_vs_Team Falcons_",
    "tournament": "Six Invitational/2026",
    "stage": "Final",
    "date": "",
    "map": "Clubhouse",
    "map_raw": "Clubhouse",
    "finished": "true",
    "atk_team": "Furia",
    "def_team": "Team Falcons",
    "atk_score": 2,
    "def_score": 4,
    "atk_deaths": 6,
    "def_deaths": 6,
    "total_deaths": 12,
    "atk_bans": [
      "Bandit",
      "Kaid",
      "Mira",
      "Thermite",
      "Capitao",
      "Grim"
    ],
    "def_bans": [
      "Thermite",
      "Grim",
      "Hibana",
      "Kaid",
      "Mira",
      "Bandit"
    ],
    "atk_operators": [],
    "def_operators": [],
    "first_attack": "atk",
    "pick": "",
    "is_flawless": false,
    "raw_map_block": "\n        |bantype=siegeX\n        |t1ban1=Bandit|t1ban2=Kaid|t1ban3=Mira|t1ban4=Thermite|t1ban5=Capitao|t1ban6=Grim\n        |t2ban1=Thermite|t2ban2=Grim|t2ban3=Hibana|t2ban4=Kaid|t2ban5=Mira|t2ban6=Bandit\n        |t1firstside=atk|t1firstsideot=\n        |t1atk=2|t1def=3|t1otatk=|t1otdef=\n        |t2atk=3|t2def=4|t2otatk=|t2otdef="
  },
  {
    "match_ref": "R1M5",
    "match_id": "R1M5_M80_vs_G2_",
    "tournament": "Six Invitational/2026",
    "stage": "Unknown",
    "date": "",
    "map": "Clubhouse",
    "map_raw": "Clubhouse",
    "finished": "skip",
    "atk_team": "M80",
    "def_team": "G2",
    "atk_score": 0,
    "def_score": 0,
    "atk_deaths": 0,
    "def_deaths": 0,
    "total_deaths": 0,
    "atk_bans": [],
    "def_bans": [],
    "atk_operators": [],
    "def_operators": [],
    "first_attack": "atk",
    "pick": "",
    "is_flawless": false,
    "raw_map_block": "\n        |bantype=siegeX\n        |t1ban1=|t1ban2=|t1ban3=|t1ban4=|t1ban5=|t1ban6=\n        |t2ban1=|t2ban2=|t2ban3=|t2ban4=|t2ban5=|t2ban6=\n        |t1firstside=|t1firstsideot=\n        |t1atk=|t1def=|t1otatk=|t1otdef=\n        |t2atk=|t2def=|t2otatk=|t2otdef="
  },
  {
    "match_ref": "R1M7",
    "match_id": "R1M7_Team Heretics_vs_Oxygen Esports_",
    "tournament": "Six Invitational/2026",
    "stage": "Unknown",
    "date": "",
    "map": "Clubhouse",
    "map_raw": "Clubhouse",
    "finished": "true",
    "atk_team": "Oxygen Esports",
    "def_team": "Team Heretics",
    "atk_score": 5,
    "def_score": 1,
    "atk_deaths": 6,
    "def_deaths": 6,
    "total_deaths": 12,
    "atk_bans": [
      "Thermite",
      "Ying",
      "Blitz",
      "Bandit",
      "Kaid",
      "Azami"
    ],
    "def_bans": [
      "Kaid",
      "Mira",
      "Bandit",
      "Capitao",
      "Grim",
      "Ying"
    ],
    "atk_operators": [],
    "def_operators": [],
    "first_attack": "def",
    "pick": "",
    "is_flawless": false,
    "raw_map_block": "\n        |bantype=siegeX\n        |t1ban1=Thermite|t1ban2=Ying|t1ban3=Blitz|t1ban4=Bandit|t1ban5=Kaid|t1ban6=Azami\n        |t2ban1=Kaid|t2ban2=Mira|t2ban3=Bandit|t2ban4=Capitao|t2ban5=Grim|t2ban6=Ying\n        |t1firstside=def|t1firstsideot=\n        |t1atk=4|t1def=1|t1otatk=|t1otdef=\n        |t2atk=5|t2def=2|t2otatk=|t2otdef="
  },
  {
    "match_ref": "R2M5",
    "match_id": "R2M5_Team Secret_vs_G2_",
    "tournament": "Six Invitational/2026",
    "stage": "Unknown",
    "date": "",
    "map": "Clubhouse",
    "map_raw": "Clubhouse",
    "finished": "true",
    "atk_team": "Team Secret",
    "def_team": "G2",
    "atk_score": 2,
    "def_score": 4,
    "atk_deaths": 6,
    "def_deaths": 6,
    "total_deaths": 12,
    "atk_bans": [
      "Bandit",
      "Kaid",
      "Azami",
      "Grim",
      "Thermite",
      "Ace"
    ],
    "def_bans": [
      "Blackbeard",
      "Capitao",
      "Grim",
      "Bandit",
      "Kaid",
      "Clash"
    ],
    "atk_operators": [],
    "def_operators": [],
    "first_attack": "atk",
    "pick": "",
    "is_flawless": false,
    "raw_map_block": "\n        |bantype=siegeX\n        |t1ban1=Bandit|t1ban2=Kaid|t1ban3=Azami|t1ban4=Grim|t1ban5=Thermite|t1ban6=Ace\n        |t2ban1=Blackbeard|t2ban2=Capitao|t2ban3=Grim|t2ban4=Bandit|t2ban5=Kaid|t2ban6=Clash\n        |t1firstside=atk|t1firstsideot=\n        |t1atk=2|t1def=3|t1otatk=|t1otdef=\n        |t2atk=3|t2def=4|t2otatk=|t2otdef="
  },
  {
    "match_ref": "R2M8",
    "match_id": "R2M8_Spacestation Gaming_vs_Shopify Rebellion_",
    "tournament": "Six Invitational/2026",
    "stage": "Lower Bracket",
    "date": "",
    "map": "Clubhouse",
    "map_raw": "Clubhouse",
    "finished": "true",
    "atk_team": "Spacestation Gaming",
    "def_team": "Shopify Rebellion",
    "atk_score": 3,
    "def_score": 3,
    "atk_deaths": 6,
    "def_deaths": 4,
    "total_deaths": 10,
    "atk_bans": [
      "Bandit",
      "Kaid",
      "Clash",
      "Capitao",
      "Montagne",
      "Ying"
    ],
    "def_bans": [
      "Capitao",
      "Grim",
      "Thermite",
      "Bandit",
      "Mira",
      "Kaid"
    ],
    "atk_operators": [],
    "def_operators": [],
    "first_attack": "atk",
    "pick": "",
    "is_flawless": false,
    "raw_map_block": "\n        |bantype=siegeX\n        |t1ban1=Bandit|t1ban2=Kaid|t1ban3=Clash|t1ban4=Capitao|t1ban5=Montagne|t1ban6=Ying\n        |t2ban1=Capitao|t2ban2=Grim|t2ban3=Thermite|t2ban4=Bandit|t2ban5=Mira|t2ban6=Kaid\n        |t1firstside=atk|t1firstsideot=\n        |t1atk=3|t1def=4|t1otatk=|t1otdef=\n        |t2atk=0|t2def=3|t2otatk=|t2otdef="
  },
  {
    "match_ref": "R3M2",
    "match_id": "R3M2_Fluxo W7M_vs_Spacestation Gaming_",
    "tournament": "Six Invitational/2026",
    "stage": "Final",
    "date": "",
    "map": "Clubhouse",
    "map_raw": "Clubhouse",
    "finished": "true",
    "atk_team": "Fluxo W7M",
    "def_team": "Spacestation Gaming",
    "atk_score": 3,
    "def_score": 3,
    "atk_deaths": 6,
    "def_deaths": 6,
    "total_deaths": 12,
    "atk_bans": [
      "Kaid",
      "Bandit",
      "Mira",
      "Grim",
      "Capitao",
      "Thermite"
    ],
    "def_bans": [
      "Capitao",
      "Thermite",
      "Grim",
      "Kaid",
      "Bandit",
      "Clash"
    ],
    "atk_operators": [],
    "def_operators": [],
    "first_attack": "atk",
    "pick": "",
    "is_flawless": false,
    "raw_map_block": "\n        |bantype=siegeX\n        |t1ban1=Kaid|t1ban2=Bandit|t1ban3=Mira|t1ban4=Grim|t1ban5=Capitao|t1ban6=Thermite\n        |t2ban1=Capitao|t2ban2=Thermite|t2ban3=Grim|t2ban4=Kaid|t2ban5=Bandit|t2ban6=Clash\n        |t1firstside=atk|t1firstsideot=def\n        |t1atk=3|t1def=3|t1otatk=0|t1otdef=1\n        |t2atk=3|t2def=3|t2otatk=1|t2otdef=1"
  },
  {
    "match_ref": "R1M1",
    "match_id": "R1M1_FaZe Clan_vs_Wildcard_",
    "tournament": "BLAST_Major/2025",
    "stage": "Unknown",
    "date": "",
    "map": "Clubhouse",
    "map_raw": "Clubhouse",
    "finished": "true",
    "atk_team": "Wildcard",
    "def_team": "FaZe Clan",
    "atk_score": 1,
    "def_score": 5,
    "atk_deaths": 6,
    "def_deaths": 4,
    "total_deaths": 10,
    "atk_bans": [
      "Montagne",
      "Thermite",
      "Ying",
      "Bandit",
      "Kaid",
      "Mira"
    ],
    "def_bans": [
      "Kaid",
      "Mira",
      "Bandit",
      "Ace",
      "Hibana",
      "Montagne"
    ],
    "atk_operators": [],
    "def_operators": [],
    "first_attack": "def",
    "pick": "",
    "is_flawless": false,
    "raw_map_block": "\n        |bantype=siegeX\n        |t1ban1=Montagne|t1ban2=Thermite|t1ban3=Ying|t1ban4=Bandit|t1ban5=Kaid|t1ban6=Mira\n        |t2ban1=Kaid|t2ban2=Mira|t2ban3=Bandit|t2ban4=Ace|t2ban5=Hibana|t2ban6=Montagne\n        |t1firstside=def|t1firstsideot=\n        |t1atk=2|t1def=5|t1otatk=|t1otdef=\n        |t2atk=1|t2def=2|t2otatk=|t2otdef="
  },
  {
    "match_ref": "R1M3",
    "match_id": "R1M3_Wildcard_vs_Ninjas in Pyjamas_",
    "tournament": "BLAST_Major/2025",
    "stage": "Unknown",
    "date": "",
    "map": "Clubhouse",
    "map_raw": "Clubhouse",
    "finished": "true",
    "atk_team": "Ninjas in Pyjamas",
    "def_team": "Wildcard",
    "atk_score": 2,
    "def_score": 4,
    "atk_deaths": 6,
    "def_deaths": 3,
    "total_deaths": 9,
    "atk_bans": [
      "Ace",
      "Hibana",
      "Thermite",
      "Kaid",
      "Mira"
    ],
    "def_bans": [
      "Kaid",
      "Bandit",
      "Mira",
      "Thermite",
      "Ace"
    ],
    "atk_operators": [],
    "def_operators": [],
    "first_attack": "def",
    "pick": "",
    "is_flawless": false,
    "raw_map_block": "\n        |bantype=siegeX\n        |t1ban1=Ace|t1ban2=Hibana|t1ban3=Thermite|t1ban4=Kaid|t1ban5=Mira|t1ban6=\n        |t2ban1=Kaid|t2ban2=Bandit|t2ban3=Mira|t2ban4=Thermite|t2ban5=Ace|t2ban6=\n        |t1firstside=def|t1firstsideot=\n        |t1atk=3|t1def=4|t1otatk=|t1otdef=\n        |t2atk=2|t2def=0|t2otatk=|t2otdef="
  },
  {
    "match_ref": "R1M4",
    "match_id": "R1M4_Team Secret_vs_Furia_",
    "tournament": "BLAST_Major/2025",
    "stage": "Final",
    "date": "",
    "map": "Clubhouse",
    "map_raw": "Clubhouse",
    "finished": "skip",
    "atk_team": "Team Secret",
    "def_team": "Furia",
    "atk_score": 0,
    "def_score": 0,
    "atk_deaths": 0,
    "def_deaths": 0,
    "total_deaths": 0,
    "atk_bans": [],
    "def_bans": [],
    "atk_operators": [],
    "def_operators": [],
    "first_attack": "atk",
    "pick": "",
    "is_flawless": false,
    "raw_map_block": "\n        |bantype=siegeX\n        |t1ban1=|t1ban2=|t1ban3=|t1ban4=|t1ban5=|t1ban6=\n        |t2ban1=|t2ban2=|t2ban3=|t2ban4=|t2ban5=|t2ban6=\n        |t1firstside=|t1firstsideot=\n        |t1atk=|t1def=|t1otatk=|t1otdef=\n        |t2atk=|t2def=|t2otatk=|t2otdef="
  },
  {
    "match_ref": "R4M2",
    "match_id": "R4M2_FaZe Clan_vs_M80_",
    "tournament": "BLAST_Major/2025",
    "stage": "Grand Final",
    "date": "",
    "map": "Clubhouse",
    "map_raw": "Clubhouse",
    "finished": "TRUE",
    "atk_team": "FaZe Clan",
    "def_team": "M80",
    "atk_score": 3,
    "def_score": 3,
    "atk_deaths": 6,
    "def_deaths": 6,
    "total_deaths": 12,
    "atk_bans": [
      "kaid",
      "bandit",
      "clash",
      "montagne",
      "blitz",
      "maverick"
    ],
    "def_bans": [
      "montagne",
      "capitao",
      "thermite",
      "kaid",
      "mira",
      "bandit"
    ],
    "atk_operators": [],
    "def_operators": [],
    "first_attack": "atk",
    "pick": "",
    "is_flawless": false,
    "raw_map_block": "\n        |bantype=siegeX\n        |t1ban1=kaid|t1ban2=bandit|t1ban3=clash|t1ban4=montagne|t1ban5=blitz|t1ban6=maverick\n        |t2ban1=montagne|t2ban2=capitao|t2ban3=thermite|t2ban4=kaid|t2ban5=mira|t2ban6=bandit\n        |t1firstside=atk|t1firstsideot=def\n        |t1atk=3|t1def=3|t1otatk=0|t1otdef=0\n        |t2atk=3|t2def=3|t2otatk=1|t2otdef=1"
  },
  {
    "match_ref": "R1M1",
    "match_id": "R1M1_W7M_vs_Unwanted_",
    "tournament": "Six Invitational/2025",
    "stage": "Unknown",
    "date": "",
    "map": "Clubhouse",
    "map_raw": "Clubhouse",
    "finished": "true",
    "atk_team": "W7M",
    "def_team": "Unwanted",
    "atk_score": 3,
    "def_score": 3,
    "atk_deaths": 6,
    "def_deaths": 6,
    "total_deaths": 12,
    "atk_bans": [
      "Thatcher",
      "Mira"
    ],
    "def_bans": [
      "Maverick",
      "Fenrir"
    ],
    "atk_operators": [],
    "def_operators": [],
    "first_attack": "atk",
    "pick": "",
    "is_flawless": false,
    "raw_map_block": "\n\t|vod=https://youtu.be/UaiPevbBvlM?si=gjYWToT5SzsDNrE2&t=23\n\t\t|t1ban1=Thatcher|t1ban2=Mira\n\t\t|t2ban1=Maverick|t2ban2=Fenrir\n\t\t|t1firstside=atk|t1firstsideot=\n\t\t|t1atk=3|t1def=2|t1otatk=|t1otdef=\n\t\t|t2atk=4|t2def=3|t2otatk=|t2otdef="
  },
  {
    "match_ref": "R1M4",
    "match_id": "R1M4_M80_vs_DarkZero_",
    "tournament": "Six Invitational/2025",
    "stage": "Final",
    "date": "",
    "map": "Clubhouse",
    "map_raw": "Clubhouse",
    "finished": "true",
    "atk_team": "DarkZero",
    "def_team": "M80",
    "atk_score": 5,
    "def_score": 1,
    "atk_deaths": 6,
    "def_deaths": 3,
    "total_deaths": 9,
    "atk_bans": [
      "Blackbeard",
      "Tubarao"
    ],
    "def_bans": [
      "Ace",
      "Mira"
    ],
    "atk_operators": [],
    "def_operators": [],
    "first_attack": "def",
    "pick": "",
    "is_flawless": false,
    "raw_map_block": "\n\t|vod=https://youtu.be/FpWPSnXmrJw?si=hkDi4IlSPxuEIduK&t=15465\n\t\t|t1ban1=Blackbeard|t1ban2=Tubarao\n\t\t|t2ban1=Ace|t2ban2=Mira\n\t\t|t1firstside=def|t1firstsideot=\n\t\t|t1atk=1|t1def=1|t1otatk=|t1otdef=\n\t\t|t2atk=5|t2def=2|t2otatk=|t2otdef="
  },
  {
    "match_ref": "R2M1",
    "match_id": "R2M1_BDS_vs_Unwanted_",
    "tournament": "Six Invitational/2025",
    "stage": "Unknown",
    "date": "",
    "map": "Clubhouse",
    "map_raw": "Clubhouse",
    "finished": "true",
    "atk_team": "Unwanted",
    "def_team": "BDS",
    "atk_score": 1,
    "def_score": 5,
    "atk_deaths": 6,
    "def_deaths": 2,
    "total_deaths": 8,
    "atk_bans": [
      "Montagne",
      "Tubarao"
    ],
    "def_bans": [
      "Maverick",
      "Kaid"
    ],
    "atk_operators": [],
    "def_operators": [],
    "first_attack": "def",
    "pick": "",
    "is_flawless": false,
    "raw_map_block": "\n\t|vod=https://youtu.be/hrIG2z7jwQI?si=1wWKkfrIoE0er3l7&t=36\n\t\t|t1ban1=Montagne|t1ban2=Tubarao\n\t\t|t2ban1=Maverick|t2ban2=Kaid\n\t\t|t1firstside=def|t1firstsideot=\n\t\t|t1atk=2|t1def=5|t1otatk=|t1otdef=\n\t\t|t2atk=1|t2def=0|t2otatk=|t2otdef="
  },
  {
    "match_ref": "R2M4",
    "match_id": "R2M4_FURIA Esports_vs_Darkzero_",
    "tournament": "Six Invitational/2025",
    "stage": "Final",
    "date": "",
    "map": "Clubhouse",
    "map_raw": "Clubhouse",
    "finished": "skip",
    "atk_team": "FURIA Esports",
    "def_team": "Darkzero",
    "atk_score": 0,
    "def_score": 0,
    "atk_deaths": 0,
    "def_deaths": 0,
    "total_deaths": 0,
    "atk_bans": [],
    "def_bans": [],
    "atk_operators": [],
    "def_operators": [],
    "first_attack": "atk",
    "pick": "",
    "is_flawless": false,
    "raw_map_block": "\n\t\t|t1ban1=|t1ban2=\n\t\t|t2ban1=|t2ban2=\n\t\t|t1firstside=|t1firstsideot=\n\t\t|t1atk=|t1def=|t1otatk=|t1otdef=\n\t\t|t2atk=|t2def=|t2otatk=|t2otdef="
  },
  {
    "match_ref": "R6M1",
    "match_id": "R6M1_Team BDS_vs_Furia_",
    "tournament": "Six Invitational/2025",
    "stage": "Lower Bracket",
    "date": "",
    "map": "Clubhouse",
    "map_raw": "Clubhouse",
    "finished": "skip",
    "atk_team": "Team BDS",
    "def_team": "Furia",
    "atk_score": 0,
    "def_score": 0,
    "atk_deaths": 0,
    "def_deaths": 0,
    "total_deaths": 0,
    "atk_bans": [],
    "def_bans": [],
    "atk_operators": [],
    "def_operators": [],
    "first_attack": "atk",
    "pick": "",
    "is_flawless": false,
    "raw_map_block": "\n\t\t|t1ban1=|t1ban2=\n\t\t|t2ban1=|t2ban2=\n\t\t|t1firstside=|t1firstsideot=\n\t\t|t1atk=|t1def=|t1otatk=|t1otdef=\n\t\t|t2atk=|t2def=|t2otatk=|t2otdef="
  },
  {
    "match_ref": "R1M5",
    "match_id": "R1M5_w7m_vs_Falcons Esport_",
    "tournament": "Six Invitational/2025",
    "stage": "Unknown",
    "date": "",
    "map": "Clubhouse",
    "map_raw": "Clubhouse",
    "finished": "true",
    "atk_team": "Falcons Esport",
    "def_team": "w7m",
    "atk_score": 2,
    "def_score": 4,
    "atk_deaths": 6,
    "def_deaths": 6,
    "total_deaths": 12,
    "atk_bans": [
      "Thatcher",
      "Mira"
    ],
    "def_bans": [
      "Capitao",
      "Kaid"
    ],
    "atk_operators": [],
    "def_operators": [],
    "first_attack": "def",
    "pick": "",
    "is_flawless": false,
    "raw_map_block": "\n\t|vod=https://youtu.be/JSAZlZws6Qw?si=1cjZgVSnO1rBIR8r&t=33\n\t\t|t1ban1=Thatcher|t1ban2=Mira\n\t\t|t2ban1=Capitao|t2ban2=Kaid\n\t\t|t1firstside=def|t1firstsideot=atk\n\t\t|t1atk=2|t1def=4|t1otatk=0|t1otdef=0\n\t\t|t2atk=2|t2def=4|t2otatk=1|t2otdef=1"
  },
  {
    "match_ref": "R1M7",
    "match_id": "R1M7_Shopify Rebellion_vs_Oxygen Esports_",
    "tournament": "Six Invitational/2025",
    "stage": "Unknown",
    "date": "",
    "map": "Clubhouse",
    "map_raw": "Clubhouse",
    "finished": "true",
    "atk_team": "Shopify Rebellion",
    "def_team": "Oxygen Esports",
    "atk_score": 4,
    "def_score": 2,
    "atk_deaths": 6,
    "def_deaths": 6,
    "total_deaths": 12,
    "atk_bans": [
      "Maverick",
      "Azami"
    ],
    "def_bans": [
      "Capitao",
      "Tubarao"
    ],
    "atk_operators": [],
    "def_operators": [],
    "first_attack": "atk",
    "pick": "",
    "is_flawless": false,
    "raw_map_block": "\n\t|vod=https://youtu.be/u_1zF-4ieJI?si=y4WzKSqfp2lVC7fB&t=4838\n\t\t|t1ban1=Maverick|t1ban2=Azami\n\t\t|t2ban1=Capitao|t2ban2=Tubarao\n\t\t|t1firstside=atk|t1firstsideot=def\n\t\t|t1atk=4|t1def=2|t1otatk=0|t1otdef=1\n\t\t|t2atk=4|t2def=2|t2otatk=1|t2otdef=1"
  },
  {
    "match_ref": "R2M6",
    "match_id": "R2M6_Virtus.pro_vs_FaZe Clan_",
    "tournament": "Six Invitational/2025",
    "stage": "Unknown",
    "date": "",
    "map": "Clubhouse",
    "map_raw": "Clubhouse",
    "finished": "true",
    "atk_team": "Virtus.pro",
    "def_team": "FaZe Clan",
    "atk_score": 2,
    "def_score": 4,
    "atk_deaths": 6,
    "def_deaths": 6,
    "total_deaths": 12,
    "atk_bans": [
      "Capitao",
      "Kaid"
    ],
    "def_bans": [
      "Montagne",
      "Mira"
    ],
    "atk_operators": [],
    "def_operators": [],
    "first_attack": "atk",
    "pick": "",
    "is_flawless": false,
    "raw_map_block": "\n\t|vod=https://youtu.be/sYYDRcEN_RI?si=7kWIhwTOGVIgMvPe&t=7270\n\t\t|t1ban1=Capitao|t1ban2=Kaid\n\t\t|t2ban1=Montagne|t2ban2=Mira\n\t\t|t1firstside=atk|t1firstsideot=\n\t\t|t1atk=2|t1def=3|t1otatk=|t1otdef=\n\t\t|t2atk=3|t2def=4|t2otatk=|t2otdef="
  },
  {
    "match_ref": "R3M1",
    "match_id": "R3M1_Falcons Esport_vs_FaZe Clan_",
    "tournament": "Six Invitational/2025",
    "stage": "Unknown",
    "date": "",
    "map": "Clubhouse",
    "map_raw": "Clubhouse",
    "finished": "true",
    "atk_team": "FaZe Clan",
    "def_team": "Falcons Esport",
    "atk_score": 3,
    "def_score": 3,
    "atk_deaths": 6,
    "def_deaths": 6,
    "total_deaths": 12,
    "atk_bans": [
      "Montagne",
      "Clash"
    ],
    "def_bans": [
      "Capitao",
      "Kaid"
    ],
    "atk_operators": [],
    "def_operators": [],
    "first_attack": "def",
    "pick": "",
    "is_flawless": false,
    "raw_map_block": "\n\t|vod=https://youtu.be/iVZ2WrfSb8E?si=c61XGm00S9aFHcVF&t=4422\n\t\t|t1ban1=Montagne|t1ban2=Clash\n\t\t|t2ban1=Capitao|t2ban2=Kaid\n\t\t|t1firstside=def|t1firstsideot=atk\n\t\t|t1atk=3|t1def=3|t1otatk=1|t1otdef=1\n\t\t|t2atk=3|t2def=3|t2otatk=0|t2otdef=0"
  },
  {
    "match_ref": "R3M2",
    "match_id": "R3M2_Oxygen Esports_vs_Unwanted_",
    "tournament": "Six Invitational/2025",
    "stage": "Final",
    "date": "",
    "map": "Clubhouse",
    "map_raw": "Clubhouse",
    "finished": "skip",
    "atk_team": "Oxygen Esports",
    "def_team": "Unwanted",
    "atk_score": 0,
    "def_score": 0,
    "atk_deaths": 0,
    "def_deaths": 0,
    "total_deaths": 0,
    "atk_bans": [],
    "def_bans": [],
    "atk_operators": [],
    "def_operators": [],
    "first_attack": "atk",
    "pick": "",
    "is_flawless": false,
    "raw_map_block": "\n\t\t|t1ban1=|t1ban2=\n\t\t|t2ban1=|t2ban2=\n\t\t|t1firstside=|t1firstsideot=\n\t\t|t1atk=|t1def=|t1otatk=|t1otdef=\n\t\t|t2atk=|t2def=|t2otatk=|t2otdef="
  },
  {
    "match_ref": "R5M1",
    "match_id": "R5M1_FaZe Clan_vs_Unwanted_",
    "tournament": "Six Invitational/2025",
    "stage": "Final",
    "date": "",
    "map": "Clubhouse",
    "map_raw": "Clubhouse",
    "finished": "true",
    "atk_team": "FaZe Clan",
    "def_team": "Unwanted",
    "atk_score": 4,
    "def_score": 2,
    "atk_deaths": 6,
    "def_deaths": 6,
    "total_deaths": 12,
    "atk_bans": [
      "Blitz",
      "Kaid"
    ],
    "def_bans": [
      "Maverick",
      "Fenrir"
    ],
    "atk_operators": [],
    "def_operators": [],
    "first_attack": "atk",
    "pick": "",
    "is_flawless": false,
    "raw_map_block": "\n\t|vod=https://youtu.be/MW67WMzbCgI?si=dQYazDDYaQe1R-II&t=7534\n\t\t|t1ban1=Blitz|t1ban2=Kaid\n\t\t|t2ban1=Maverick|t2ban2=Fenrir\n\t\t|t1firstside=atk|t1firstsideot=\n\t\t|t1atk=4|t1def=3|t1otatk=|t1otdef=\n\t\t|t2atk=3|t2def=2|t2otatk=|t2otdef="
  },
  {
    "match_ref": "R6M2",
    "match_id": "R6M2_FURIA_vs_FaZe Clan_",
    "tournament": "Six Invitational/2025",
    "stage": "Grand Final",
    "date": "",
    "map": "Clubhouse",
    "map_raw": "Clubhouse",
    "finished": "true",
    "atk_team": "FURIA",
    "def_team": "FaZe Clan",
    "atk_score": 2,
    "def_score": 4,
    "atk_deaths": 6,
    "def_deaths": 6,
    "total_deaths": 12,
    "atk_bans": [
      "Nomad",
      "Kaid"
    ],
    "def_bans": [
      "Montagne",
      "Bandit"
    ],
    "atk_operators": [],
    "def_operators": [],
    "first_attack": "atk",
    "pick": "",
    "is_flawless": false,
    "raw_map_block": "\n\t|vod=https://youtu.be/MW67WMzbCgI?si=OBBUr33hW6y3nQRA&t=14442\n\t\t|t1ban1=Nomad|t1ban2=Kaid\n\t\t|t2ban1=Montagne|t2ban2=Bandit\n\t\t|t1firstside=atk|t1firstsideot=\n\t\t|t1atk=2|t1def=3|t1otatk=|t1otdef=\n\t\t|t2atk=3|t2def=4|t2otatk=|t2otdef="
  },
  {
    "match_ref": "R7M1",
    "match_id": "R7M1_Team BDS_vs_FaZe Clan_2025-02-16_1530",
    "tournament": "Six Invitational/2025",
    "stage": "Final",
    "date": "2025-02-16 15:30",
    "map": "Clubhouse",
    "map_raw": "Clubhouse",
    "finished": "true",
    "atk_team": "FaZe Clan",
    "def_team": "Team BDS",
    "atk_score": 4,
    "def_score": 2,
    "atk_deaths": 6,
    "def_deaths": 5,
    "total_deaths": 11,
    "atk_bans": [
      "Maverick",
      "Valkyrie"
    ],
    "def_bans": [
      "Deimos",
      "Kaid"
    ],
    "atk_operators": [],
    "def_operators": [],
    "first_attack": "def",
    "pick": "team_b",
    "is_flawless": false,
    "raw_map_block": "\n\t\t|t1ban1=Maverick|t1ban2=Valkyrie\n\t\t|t2ban1=Deimos|t2ban2=Kaid\n\t\t|t1firstside=def|t1firstsideot=\n\t\t|t1atk=2|t1def=2|t1otatk=|t1otdef=\n\t\t|t2atk=4|t2def=3|t2otatk=|t2otdef="
  },
  {
    "match_ref": "R7M1",
    "match_id": "R7M1_FaZe Clan_vs_Team Secret_",
    "tournament": "Six Invitational/2026",
    "stage": "Final",
    "date": "",
    "map": "Clubhouse",
    "map_raw": "Clubhouse",
    "finished": "skip",
    "atk_team": "FaZe Clan",
    "def_team": "Team Secret",
    "atk_score": 0,
    "def_score": 0,
    "atk_deaths": 0,
    "def_deaths": 0,
    "total_deaths": 0,
    "atk_bans": [],
    "def_bans": [],
    "atk_operators": [],
    "def_operators": [],
    "first_attack": "atk",
    "pick": "",
    "is_flawless": false,
    "raw_map_block": "\n\t\t|bantype=siegeX\n\t\t|t1ban1=|t1ban2=|t1ban3=|t1ban4=|t1ban5=|t1ban6=\n        |t2ban1=|t2ban2=|t2ban3=|t2ban4=|t2ban5=|t2ban6=\n        |t1firstside=|t1firstsideot=\n        |t1atk=|t1def=|t1otatk=|t1otdef=\n        |t2atk=|t2def=|t2otatk=|t2otdef="
  }
]